redskyAPI/__init__.py
redskyAPI/skychat.py
redskyAPI-1.0.3.dist-info/DESCRIPTION.rst
redskyAPI-1.0.3.dist-info/METADATA
redskyAPI-1.0.3.dist-info/RECORD
redskyAPI-1.0.3.dist-info/WHEEL
redskyAPI-1.0.3.dist-info/metadata.json
redskyAPI-1.0.3.dist-info/top_level.txt
