Metadata-Version: 2.0
Name: redskyAPI
Version: 1.0.3
Summary: Client API for the redsky.fr chat
Home-page: http://beerstorm.info/redskyAPI
Author: Beerstorm
Author-email: beerstorm.emberbeard@gmail.com
License: GPLv3
Platform: UNKNOWN
Requires-Dist: requests
Requires-Dist: socketIO-client
